gobotics/__init__.py
gobotics/godotbridge.py
gobotics/helper.py
pygobotics-0.3.0.dist-info/METADATA
pygobotics-0.3.0.dist-info/WHEEL
pygobotics-0.3.0.dist-info/top_level.txt
pygobotics-0.3.0.dist-info/RECORD
